Workbook

Sheet DashboardBlack-Scholes Option P
F2: Black-Scholes Option Pricing Dashboard
D6: Model Inputs | H6: Option Prices | M6: Greeks Summary
D8: Spot Price | E8: =Input_Pricing!D6 -> 100 | H8: Call Price | J8: =Input_Pricing!C21 -> 10.450584 | M8: Delta Call | N8: =Input_Pricing!C30 -> 0.63683065
D9: Strike Price | E9: =Input_Pricing!D7 -> 100 | H9: Put Price | J9: =Input_Pricing!C22 -> 5.573526 | M9: Delta Put | N9: =Input_Pricing!C31 -> -0.36316935
D10: Time to Maturity | E10: =Input_Pricing!D8 -> 1 | M10: Gamma | N10: =Input_Pricing!C32 -> 0.018762017
D11: Risk-Free Rate | E11: =Input_Pricing!D9 -> 0.05 | M11: Vega | N11: =Input_Pricing!C33 -> 0.37524035
D12: Volatility | E12: =Input_Pricing!D10 -> 0.2 | M12: Theta Call | N12: =Input_Pricing!C34 -> -0.017572678
D13: Dividend Yield | E13: =Input_Pricing!D11 -> 0 | M13: Theta Put | N13: =Input_Pricing!C35 -> -0.0045421381
M14: Rho Call | N14: =Input_Pricing!C36 -> 0.53232482
M15: Rho Put | N15: =Input_Pricing!C37 -> -0.41890461
H16: Key Interpretation

Sheet Input_Pricing
D2: Black-Scholes Option Pricing Model
B5: Input | C5: Symbol | D5: Value | E5: Description
B6: Spot price | C6: S0 | D6: 100 | E6: Current price of the underlying asset
B7: Strike price | C7: K | D7: 100 | E7: Exercise price of the option
B8: Time to maturity | C8: T | D8: 1 | E8: Time until expiration in years
B9: Risk free rate | C9: r | D9: 0.05 | E9: Annual Risk-free interest rate
B10: Volatility | C10: σ | D10: 0.2 | E10: Annual vol of the underlying asset
B11: dividend yield | C11: q | D11: 0 | E11: Annual dividend yield
B14: Calculation | C14: Formula / Value | D14: Explanation | E14: Theorical formula
B15: d1 | C15: =(LN(D6/D7)+(D9-D11+0.5*D10^2)*D8)/(D10*SQRT(D8)) -> 0.35 | D15: Standardised distance to the strike adjusted for drift and volatility | E15: d1 = [ln(S0/K) + (r - q + 0.5σ²)T] / [σ√T]
B16: d2 | C16: =C15-D10*SQRT(D8) -> 0.15 | D16: d2 equals d1 minus one volatility-adjusted time step | E16: d2 = d1 - σ√T
B17: N(d1) | C17: =_xlfn.NORM.S.DIST(C15,TRUE) -> 0.63683065 | D17: N(d1): Cumulative standard normal probability up to d1, mainly used in the call formula and related to call Delta.
B18: N(d2) | C18: =_xlfn.NORM.S.DIST(C16,TRUE) -> 0.55961769 | D18: N(d2): Cumulative standard normal probability up to d2, used in the call formula.
B19: N(-d1) | C19: =_xlfn.NORM.S.DIST(-C15,TRUE) -> 0.36316935 | D19: N(-d1): Cumulative standard normal probability up to -d1, used in the put formula.
B20: N(-d2) | C20: =_xlfn.NORM.S.DIST(-C16,TRUE) -> 0.44038231 | D20: N(-d2): Cumulative standard normal probability up to -d2, used in the put formula.
B21: Call | C21: =D6*EXP(-D11*D8)*C17-D7*EXP(-D9*D8)*C18 -> 10.450584 | D21: Call: Expected discounted value of receiving the underlying minus the expected discounted cost of paying the strike. | E21: Call = S0 e^(-qT) N(d1) - K e^(-rT) N(d2)
B22: Put | C22: =D7*EXP(-D9*D8)*C20-D6*EXP(-D11*D8)*C19 -> 5.573526 | D22: Put: Expected discounted value of receiving the strike minus the expected value of delivering the underlying. | E22: Put = K e^(-rT) N(-d2) - S0 e^(-qT) N(-d1)
B23: Put-call parity LHS | C23: =C21-C22 -> 4.8770575 | D23: Put-call parity LHS: Difference between the call price and the put price.
B24: Put-call parity RHS | C24: =D6*EXP(-D11*D8)-D7*EXP(-D9*D8) -> 4.8770575 | D24: Put-call parity RHS: Present value of the dividend-adjusted underlying minus the present value of the strike. | E24: S0 e^(-qT) - K e^(-rT)
B25: Parity difference | C25: =C23-C24 -> 0 | D25: Parity difference: Difference between both sides of put-call parity. It should be close to zero if the formulas are correct.
B28: Greeks | C28: Formula / Value | D28: Explanation | E28: Theorical formula
B29: phi(d1) | C29: =_xlfn.NORM.S.DIST(C15,FALSE) -> 0.37524035 | D29: phi(d1): Standard normal density at d1, used to calculate Gamma, Vega and Theta.
B30: Delta Call | C30: =EXP(-D11*D8)*C17 -> 0.63683065 | D30: If the underlying increases by 1, the call price increases by approximately 0,64. | E30: Delta call = e^(-qT) N(d1)
B31: Delta Put | C31: =EXP(-D11*D8)*(C17-1) -> -0.36316935 | D31: If the underlying increases by 1, the put price decreases by approximately 0,36. | E31: Delta put = e^(-qT) [N(d1) - 1]
B32: Gamma | C32: =EXP(-D11*D8)*C29/(D6*D10*SQRT(D8)) -> 0.018762017 | D32: Gamma measures the curvature of the option price. It shows how quickly Delta changes when the underlying moves. | E32: Gamma = e^(-qT) φ(d1) / [S0 σ √T]
B33: Vega | C33: =D6*EXP(-D11*D8)*C29*SQRT(D8)/100 -> 0.37524035 | D33: If volatility increases by 1 percentage point, the option price increases by approximately 0,38. | E33: Vega = S0 e^(-qT) φ(d1) √T / 100
B34: Theta Call | C34: =(-(D6*EXP(-D11*D8)*C29*D10)/(2*SQRT(D8))-D9*D7*EXP(-D9*D8)*C18+D11*D6*EXP(-D11*D8)*C17)/365 -> -0.017572678 | D34: The call loses approximately 0,018 per day due to time decay, all else equal. | E34: Theta call = -[S0 e^(-qT) φ(d1) σ] / [2√T] - rK e^(-rT)N(d2) + qS0 e^(-qT)N(d1)
B35: Theta Put | C35: =(-(D6*EXP(-D11*D8)*C29*D10)/(2*SQRT(D8))+D9*D7*EXP(-D9*D8)*C20-D11*D6*EXP(-D11*D8)*C19)/365 -> -0.0045421381 | D35: Theta Put: The put loses approximately 0,005 per day due to time decay, all else equal. | E35: Theta put = -[S0 e^(-qT) φ(d1) σ] / [2√T] + rK e^(-rT)N(-d2) - qS0 e^(-qT)N(-d1)
B36: Rho Call | C36: =D7*D8*EXP(-D9*D8)*C18/100 -> 0.53232482 | D36: If interest rates increase by 1 percentage point, the call price increases by approximately 0,53. | E36: Rho call = K T e^(-rT) N(d2) / 100
B37: Rho Put | C37: =-D7*D8*EXP(-D9*D8)*C20/100 -> -0.41890461 | D37: Rho Put: If interest rates increase by 1 percentage point, the put price decreases by approximately 0,42. | E37: Rho put = -K T e^(-rT) N(-d2) / 100

Sheet SensitivityBlack-Scholes Sens
E2: Black-Scholes Sensitivity Analysis
C7: Spot Price | D7: d1 | E7: d2 | F7: N(d1) | G7: N(d2) | H7: N(-d1) | I7: N(-d2) | J7: Call Pirce | K7: Put Price | M7: Volatility | N7: d1 | O7: d2 | P7: N(d1) | Q7: N(d2) | R7: N(-d1) | S7: N(-d2) | T7: Call Price | U7: Put Price | W7: Time to maturity | X7: d1 | Y7: d2 | Z7: N(d1) | AA7: N(d2) | AB7: N(-d1) | AC7: N(-d2) | AD7: Call Price | AE7: Put Price
C8: 60 | D8: =(LN(C8/Input_Pricing!$D$7)+(Input_Pricing!$D$9-Input_Pricing!$D$11+0.5*Input_Pricing!$D$10^2)*Input_Pricing!$D$8)/(Input_Pricing!$D$10*SQRT(Input_Pricing!$D$8)) -> -2.2041281 | E8: =D8-Input_Pricing!$D$10*SQRT(Input_Pricing!$D$8) -> -2.4041281 | F8: =_xlfn.NORM.S.DIST(D8,TRUE) -> 0.013757668 | G8: =_xlfn.NORM.S.DIST(E8,TRUE) -> 0.0081055454 | H8: =_xlfn.NORM.S.DIST(-D8,TRUE) -> 0.98624233 | I8: =_xlfn.NORM.S.DIST(-E8,TRUE) -> 0.99189445 | J8: =C8*EXP(-Input_Pricing!$D$11*Input_Pricing!$D$8)*F8-Input_Pricing!$D$7*EXP(-Input_Pricing!$D$9*Input_Pricing!$D$8)*G8 -> 0.05443673 | K8: =Input_Pricing!$D$7*EXP(-Input_Pricing!$D$9*Input_Pricing!$D$8)*I8-C8*EXP(-Input_Pricing!$D$11*Input_Pricing!$D$8)*H8 -> 35.177379 | M8: 0.05 | N8: =(LN(Input_Pricing!$D$6/Input_Pricing!$D$7)+(Input_Pricing!$D$9-Input_Pricing!$D$11+0.5*M8^2)*Input_Pricing!$D$8)/(M8*SQRT(Input_Pricing!$D$8)) -> 1.025 | O8: =N8-M8*SQRT(Input_Pricing!$D$8) -> 0.975 | P8: =_xlfn.NORM.S.DIST(N8,TRUE) -> 0.84731841 | Q8: =_xlfn.NORM.S.DIST(O8,TRUE) -> 0.83521987 | R8: =_xlfn.NORM.S.DIST(-N8,TRUE) -> 0.15268159 | S8: =_xlfn.NORM.S.DIST(-O8,TRUE) -> 0.16478013 | T8: =Input_Pricing!$D$6*EXP(-Input_Pricing!$D$11*Input_Pricing!$D$8)*P8-Input_Pricing!$D$7*EXP(-Input_Pricing!$D$9*Input_Pricing!$D$8)*Q8 -> 5.283269 | U8: =Input_Pricing!$D$7*EXP(-Input_Pricing!$D$9*Input_Pricing!$D$8)*S8-Input_Pricing!$D$6*EXP(-Input_Pricing!$D$11*Input_Pricing!$D$8)*R8 -> 0.40621144 | W8: 0.1 | X8: =(LN(Input_Pricing!$D$6/Input_Pricing!$D$7)+(Input_Pricing!$D$9-Input_Pricing!$D$11+0.5*Input_Pricing!$D$10^2)*W8)/(Input_Pricing!$D$10*SQRT(W8)) -> 0.11067972 | Y8: =X8-Input_Pricing!$D$10*SQRT(W8) -> 0.047434165 | Z8: =_xlfn.NORM.S.DIST(X8,TRUE) -> 0.54406484 | AA8: =_xlfn.NORM.S.DIST(Y8,TRUE) -> 0.5189164 | AB8: =_xlfn.NORM.S.DIST(-X8,TRUE) -> 0.45593516 | AC8: =_xlfn.NORM.S.DIST(-Y8,TRUE) -> 0.4810836 | AD8: =Input_Pricing!$D$6*EXP(-Input_Pricing!$D$11*W8)*Z8-Input_Pricing!$D$7*EXP(-Input_Pricing!$D$9*W8)*AA8 -> 2.7736541 | AE8: =Input_Pricing!$D$7*EXP(-Input_Pricing!$D$9*W8)*AC8-Input_Pricing!$D$6*EXP(-Input_Pricing!$D$11*W8)*AB8 -> 2.2749021
C9: 65 | D9: =(LN(C9/Input_Pricing!$D$7)+(Input_Pricing!$D$9-Input_Pricing!$D$11+0.5*Input_Pricing!$D$10^2)*Input_Pricing!$D$8)/(Input_Pricing!$D$10*SQRT(Input_Pricing!$D$8)) -> -1.8039146 | E9: =D9-Input_Pricing!$D$10*SQRT(Input_Pricing!$D$8) -> -2.0039146 | F9: =_xlfn.NORM.S.DIST(D9,TRUE) -> 0.035622349 | G9: =_xlfn.NORM.S.DIST(E9,TRUE) -> 0.022539606 | H9: =_xlfn.NORM.S.DIST(-D9,TRUE) -> 0.96437765 | I9: =_xlfn.NORM.S.DIST(-E9,TRUE) -> 0.97746039 | J9: =C9*EXP(-Input_Pricing!$D$11*Input_Pricing!$D$8)*F9-Input_Pricing!$D$7*EXP(-Input_Pricing!$D$9*Input_Pricing!$D$8)*G9 -> 0.1714191 | K9: =Input_Pricing!$D$7*EXP(-Input_Pricing!$D$9*Input_Pricing!$D$8)*I9-C9*EXP(-Input_Pricing!$D$11*Input_Pricing!$D$8)*H9 -> 30.294362 | M9: 0.1 | N9: =(LN(Input_Pricing!$D$6/Input_Pricing!$D$7)+(Input_Pricing!$D$9-Input_Pricing!$D$11+0.5*M9^2)*Input_Pricing!$D$8)/(M9*SQRT(Input_Pricing!$D$8)) -> 0.55 | O9: =N9-M9*SQRT(Input_Pricing!$D$8) -> 0.45 | P9: =_xlfn.NORM.S.DIST(N9,TRUE) -> 0.70884031 | Q9: =_xlfn.NORM.S.DIST(O9,TRUE) -> 0.67364478 | R9: =_xlfn.NORM.S.DIST(-N9,TRUE) -> 0.29115969 | S9: =_xlfn.NORM.S.DIST(-O9,TRUE) -> 0.32635522 | T9: =Input_Pricing!$D$6*EXP(-Input_Pricing!$D$11*Input_Pricing!$D$8)*P9-Input_Pricing!$D$7*EXP(-Input_Pricing!$D$9*Input_Pricing!$D$8)*Q9 -> 6.8049577 | U9: =Input_Pricing!$D$7*EXP(-Input_Pricing!$D$9*Input_Pricing!$D$8)*S9-Input_Pricing!$D$6*EXP(-Input_Pricing!$D$11*Input_Pricing!$D$8)*R9 -> 1.9279002 | W9: 0.25 | X9: =(LN(Input_Pricing!$D$6/Input_Pricing!$D$7)+(Input_Pricing!$D$9-Input_Pricing!$D$11+0.5*Input_Pricing!$D$10^2)*W9)/(Input_Pricing!$D$10*SQRT(W9)) -> 0.175 | Y9: =X9-Input_Pricing!$D$10*SQRT(W9) -> 0.075 | Z9: =_xlfn.NORM.S.DIST(X9,TRUE) -> 0.56946018 | AA9: =_xlfn.NORM.S.DIST(Y9,TRUE) -> 0.52989264 | AB9: =_xlfn.NORM.S.DIST(-X9,TRUE) -> 0.43053982 | AC9: =_xlfn.NORM.S.DIST(-Y9,TRUE) -> 0.47010736 | AD9: =Input_Pricing!$D$6*EXP(-Input_Pricing!$D$11*W9)*Z9-Input_Pricing!$D$7*EXP(-Input_Pricing!$D$9*W9)*AA9 -> 4.6149971 | AE9: =Input_Pricing!$D$7*EXP(-Input_Pricing!$D$9*W9)*AC9-Input_Pricing!$D$6*EXP(-Input_Pricing!$D$11*W9)*AB9 -> 3.3727772
C10: 70 | D10: =(LN(C10/Input_Pricing!$D$7)+(Input_Pricing!$D$9-Input_Pricing!$D$11+0.5*Input_Pricing!$D$10^2)*Input_Pricing!$D$8)/(Input_Pricing!$D$10*SQRT(Input_Pricing!$D$8)) -> -1.4333747 | E10: =D10-Input_Pricing!$D$10*SQRT(Input_Pricing!$D$8) -> -1.6333747 | F10: =_xlfn.NORM.S.DIST(D10,TRUE) -> 0.075875389 | G10: =_xlfn.NORM.S.DIST(E10,TRUE) -> 0.051195105 | H10: =_xlfn.NORM.S.DIST(-D10,TRUE) -> 0.92412461 | I10: =_xlfn.NORM.S.DIST(-E10,TRUE) -> 0.94880489 | J10: =C10*EXP(-Input_Pricing!$D$11*Input_Pricing!$D$8)*F10-Input_Pricing!$D$7*EXP(-Input_Pricing!$D$9*Input_Pricing!$D$8)*G10 -> 0.44144821 | K10: =Input_Pricing!$D$7*EXP(-Input_Pricing!$D$9*Input_Pricing!$D$8)*I10-C10*EXP(-Input_Pricing!$D$11*Input_Pricing!$D$8)*H10 -> 25.564391 | M10: 0.15 | N10: =(LN(Input_Pricing!$D$6/Input_Pricing!$D$7)+(Input_Pricing!$D$9-Input_Pricing!$D$11+0.5*M10^2)*Input_Pricing!$D$8)/(M10*SQRT(Input_Pricing!$D$8)) -> 0.40833333 | O10: =N10-M10*SQRT(Input_Pricing!$D$8) -> 0.25833333 | P10: =_xlfn.NORM.S.DIST(N10,TRUE) -> 0.65848551 | Q10: =_xlfn.NORM.S.DIST(O10,TRUE) -> 0.60192517 | R10: =_xlfn.NORM.S.DIST(-N10,TRUE) -> 0.34151449 | S10: =_xlfn.NORM.S.DIST(-O10,TRUE) -> 0.39807483 | T10: =Input_Pricing!$D$6*EXP(-Input_Pricing!$D$11*Input_Pricing!$D$8)*P10-Input_Pricing!$D$7*EXP(-Input_Pricing!$D$9*Input_Pricing!$D$8)*Q10 -> 8.5916583 | U10: =Input_Pricing!$D$7*EXP(-Input_Pricing!$D$9*Input_Pricing!$D$8)*S10-Input_Pricing!$D$6*EXP(-Input_Pricing!$D$11*Input_Pricing!$D$8)*R10 -> 3.7146008 | W10: 0.5 | X10: =(LN(Input_Pricing!$D$6/Input_Pricing!$D$7)+(Input_Pricing!$D$9-Input_Pricing!$D$11+0.5*Input_Pricing!$D$10^2)*W10)/(Input_Pricing!$D$10*SQRT(W10)) -> 0.24748737 | Y10: =X10-Input_Pricing!$D$10*SQRT(W10) -> 0.10606602 | Z10: =_xlfn.NORM.S.DIST(X10,TRUE) -> 0.59773447 | AA10: =_xlfn.NORM.S.DIST(Y10,TRUE) -> 0.54223501 | AB10: =_xlfn.NORM.S.DIST(-X10,TRUE) -> 0.40226553 | AC10: =_xlfn.NORM.S.DIST(-Y10,TRUE) -> 0.45776499 | AD10: =Input_Pricing!$D$6*EXP(-Input_Pricing!$D$11*W10)*Z10-Input_Pricing!$D$7*EXP(-Input_Pricing!$D$9*W10)*AA10 -> 6.8887286 | AE10: =Input_Pricing!$D$7*EXP(-Input_Pricing!$D$9*W10)*AC10-Input_Pricing!$D$6*EXP(-Input_Pricing!$D$11*W10)*AB10 -> 4.4197198
C11: 75 | D11: =(LN(C11/Input_Pricing!$D$7)+(Input_Pricing!$D$9-Input_Pricing!$D$11+0.5*Input_Pricing!$D$10^2)*Input_Pricing!$D$8)/(Input_Pricing!$D$10*SQRT(Input_Pricing!$D$8)) -> -1.0884104 | E11: =D11-Input_Pricing!$D$10*SQRT(Input_Pricing!$D$8) -> -1.2884104 | F11: =_xlfn.NORM.S.DIST(D11,TRUE) -> 0.13820699 | G11: =_xlfn.NORM.S.DIST(E11,TRUE) -> 0.098801577 | H11: =_xlfn.NORM.S.DIST(-D11,TRUE) -> 0.86179301 | I11: =_xlfn.NORM.S.DIST(-E11,TRUE) -> 0.90119842 | J11: =C11*EXP(-Input_Pricing!$D$11*Input_Pricing!$D$8)*F11-Input_Pricing!$D$7*EXP(-Input_Pricing!$D$9*Input_Pricing!$D$8)*G11 -> 0.96722787 | K11: =Input_Pricing!$D$7*EXP(-Input_Pricing!$D$9*Input_Pricing!$D$8)*I11-C11*EXP(-Input_Pricing!$D$11*Input_Pricing!$D$8)*H11 -> 21.09017 | M11: 0.2 | N11: =(LN(Input_Pricing!$D$6/Input_Pricing!$D$7)+(Input_Pricing!$D$9-Input_Pricing!$D$11+0.5*M11^2)*Input_Pricing!$D$8)/(M11*SQRT(Input_Pricing!$D$8)) -> 0.35 | O11: =N11-M11*SQRT(Input_Pricing!$D$8) -> 0.15 | P11: =_xlfn.NORM.S.DIST(N11,TRUE) -> 0.63683065 | Q11: =_xlfn.NORM.S.DIST(O11,TRUE) -> 0.55961769 | R11: =_xlfn.NORM.S.DIST(-N11,TRUE) -> 0.36316935 | S11: =_xlfn.NORM.S.DIST(-O11,TRUE) -> 0.44038231 | T11: =Input_Pricing!$D$6*EXP(-Input_Pricing!$D$11*Input_Pricing!$D$8)*P11-Input_Pricing!$D$7*EXP(-Input_Pricing!$D$9*Input_Pricing!$D$8)*Q11 -> 10.450584 | U11: =Input_Pricing!$D$7*EXP(-Input_Pricing!$D$9*Input_Pricing!$D$8)*S11-Input_Pricing!$D$6*EXP(-Input_Pricing!$D$11*Input_Pricing!$D$8)*R11 -> 5.573526 | W11: 0.75 | X11: =(LN(Input_Pricing!$D$6/Input_Pricing!$D$7)+(Input_Pricing!$D$9-Input_Pricing!$D$11+0.5*Input_Pricing!$D$10^2)*W11)/(Input_Pricing!$D$10*SQRT(W11)) -> 0.30310889 | Y11: =X11-Input_Pricing!$D$10*SQRT(W11) -> 0.12990381 | Z11: =_xlfn.NORM.S.DIST(X11,TRUE) -> 0.61909656 | AA11: =_xlfn.NORM.S.DIST(Y11,TRUE) -> 0.55167874 | AB11: =_xlfn.NORM.S.DIST(-X11,TRUE) -> 0.38090344 | AC11: =_xlfn.NORM.S.DIST(-Y11,TRUE) -> 0.44832126 | AD11: =Input_Pricing!$D$6*EXP(-Input_Pricing!$D$11*W11)*Z11-Input_Pricing!$D$7*EXP(-Input_Pricing!$D$9*W11)*AA11 -> 8.7722683 | AE11: =Input_Pricing!$D$7*EXP(-Input_Pricing!$D$9*W11)*AC11-Input_Pricing!$D$6*EXP(-Input_Pricing!$D$11*W11)*AB11 -> 5.09171
C12: 80 | D12: =(LN(C12/Input_Pricing!$D$7)+(Input_Pricing!$D$9-Input_Pricing!$D$11+0.5*Input_Pricing!$D$10^2)*Input_Pricing!$D$8)/(Input_Pricing!$D$10*SQRT(Input_Pricing!$D$8)) -> -0.76571776 | E12: =D12-Input_Pricing!$D$10*SQRT(Input_Pricing!$D$8) -> -0.96571776 | F12: =_xlfn.NORM.S.DIST(D12,TRUE) -> 0.22192213 | G12: =_xlfn.NORM.S.DIST(E12,TRUE) -> 0.16709272 | H12: =_xlfn.NORM.S.DIST(-D12,TRUE) -> 0.77807787 | I12: =_xlfn.NORM.S.DIST(-E12,TRUE) -> 0.83290728 | J12: =C12*EXP(-Input_Pricing!$D$11*Input_Pricing!$D$8)*F12-Input_Pricing!$D$7*EXP(-Input_Pricing!$D$9*Input_Pricing!$D$8)*G12 -> 1.8594196 | K12: =Input_Pricing!$D$7*EXP(-Input_Pricing!$D$9*Input_Pricing!$D$8)*I12-C12*EXP(-Input_Pricing!$D$11*Input_Pricing!$D$8)*H12 -> 16.982362 | M12: 0.25 | N12: =(LN(Input_Pricing!$D$6/Input_Pricing!$D$7)+(Input_Pricing!$D$9-Input_Pricing!$D$11+0.5*M12^2)*Input_Pricing!$D$8)/(M12*SQRT(Input_Pricing!$D$8)) -> 0.325 | O12: =N12-M12*SQRT(Input_Pricing!$D$8) -> 0.075 | P12: =_xlfn.NORM.S.DIST(N12,TRUE) -> 0.62740946 | Q12: =_xlfn.NORM.S.DIST(O12,TRUE) -> 0.52989264 | R12: =_xlfn.NORM.S.DIST(-N12,TRUE) -> 0.37259054 | S12: =_xlfn.NORM.S.DIST(-O12,TRUE) -> 0.47010736 | T12: =Input_Pricing!$D$6*EXP(-Input_Pricing!$D$11*Input_Pricing!$D$8)*P12-Input_Pricing!$D$7*EXP(-Input_Pricing!$D$9*Input_Pricing!$D$8)*Q12 -> 12.335999 | U12: =Input_Pricing!$D$7*EXP(-Input_Pricing!$D$9*Input_Pricing!$D$8)*S12-Input_Pricing!$D$6*EXP(-Input_Pricing!$D$11*Input_Pricing!$D$8)*R12 -> 7.4589414 | W12: 1 | X12: =(LN(Input_Pricing!$D$6/Input_Pricing!$D$7)+(Input_Pricing!$D$9-Input_Pricing!$D$11+0.5*Input_Pricing!$D$10^2)*W12)/(Input_Pricing!$D$10*SQRT(W12)) -> 0.35 | Y12: =X12-Input_Pricing!$D$10*SQRT(W12) -> 0.15 | Z12: =_xlfn.NORM.S.DIST(X12,TRUE) -> 0.63683065 | AA12: =_xlfn.NORM.S.DIST(Y12,TRUE) -> 0.55961769 | AB12: =_xlfn.NORM.S.DIST(-X12,TRUE) -> 0.36316935 | AC12: =_xlfn.NORM.S.DIST(-Y12,TRUE) -> 0.44038231 | AD12: =Input_Pricing!$D$6*EXP(-Input_Pricing!$D$11*W12)*Z12-Input_Pricing!$D$7*EXP(-Input_Pricing!$D$9*W12)*AA12 -> 10.450584 | AE12: =Input_Pricing!$D$7*EXP(-Input_Pricing!$D$9*W12)*AC12-Input_Pricing!$D$6*EXP(-Input_Pricing!$D$11*W12)*AB12 -> 5.573526
C13: 85 | D13: =(LN(C13/Input_Pricing!$D$7)+(Input_Pricing!$D$9-Input_Pricing!$D$11+0.5*Input_Pricing!$D$10^2)*Input_Pricing!$D$8)/(Input_Pricing!$D$10*SQRT(Input_Pricing!$D$8)) -> -0.46259465 | E13: =D13-Input_Pricing!$D$10*SQRT(Input_Pricing!$D$8) -> -0.66259465 | F13: =_xlfn.NORM.S.DIST(D13,TRUE) -> 0.32182747 | G13: =_xlfn.NORM.S.DIST(E13,TRUE) -> 0.2537951 | H13: =_xlfn.NORM.S.DIST(-D13,TRUE) -> 0.67817253 | I13: =_xlfn.NORM.S.DIST(-E13,TRUE) -> 0.7462049 | J13: =C13*EXP(-Input_Pricing!$D$11*Input_Pricing!$D$8)*F13-Input_Pricing!$D$7*EXP(-Input_Pricing!$D$9*Input_Pricing!$D$8)*G13 -> 3.2135986 | K13: =Input_Pricing!$D$7*EXP(-Input_Pricing!$D$9*Input_Pricing!$D$8)*I13-C13*EXP(-Input_Pricing!$D$11*Input_Pricing!$D$8)*H13 -> 13.336541 | M13: 0.3 | N13: =(LN(Input_Pricing!$D$6/Input_Pricing!$D$7)+(Input_Pricing!$D$9-Input_Pricing!$D$11+0.5*M13^2)*Input_Pricing!$D$8)/(M13*SQRT(Input_Pricing!$D$8)) -> 0.31666667 | O13: =N13-M13*SQRT(Input_Pricing!$D$8) -> 0.016666667 | P13: =_xlfn.NORM.S.DIST(N13,TRUE) -> 0.62425173 | Q13: =_xlfn.NORM.S.DIST(O13,TRUE) -> 0.50664873 | R13: =_xlfn.NORM.S.DIST(-N13,TRUE) -> 0.37574827 | S13: =_xlfn.NORM.S.DIST(-O13,TRUE) -> 0.49335127 | T13: =Input_Pricing!$D$6*EXP(-Input_Pricing!$D$11*Input_Pricing!$D$8)*P13-Input_Pricing!$D$7*EXP(-Input_Pricing!$D$9*Input_Pricing!$D$8)*Q13 -> 14.231255 | U13: =Input_Pricing!$D$7*EXP(-Input_Pricing!$D$9*Input_Pricing!$D$8)*S13-Input_Pricing!$D$6*EXP(-Input_Pricing!$D$11*Input_Pricing!$D$8)*R13 -> 9.3541972 | W13: 1.5 | X13: =(LN(Input_Pricing!$D$6/Input_Pricing!$D$7)+(Input_Pricing!$D$9-Input_Pricing!$D$11+0.5*Input_Pricing!$D$10^2)*W13)/(Input_Pricing!$D$10*SQRT(W13)) -> 0.4286607 | Y13: =X13-Input_Pricing!$D$10*SQRT(W13) -> 0.18371173 | Z13: =_xlfn.NORM.S.DIST(X13,TRUE) -> 0.66591492 | AA13: =_xlfn.NORM.S.DIST(Y13,TRUE) -> 0.5728802 | AB13: =_xlfn.NORM.S.DIST(-X13,TRUE) -> 0.33408508 | AC13: =_xlfn.NORM.S.DIST(-Y13,TRUE) -> 0.4271198 | AD13: =Input_Pricing!$D$6*EXP(-Input_Pricing!$D$11*W13)*Z13-Input_Pricing!$D$7*EXP(-Input_Pricing!$D$9*W13)*AA13 -> 13.442905 | AE13: =Input_Pricing!$D$7*EXP(-Input_Pricing!$D$9*W13)*AC13-Input_Pricing!$D$6*EXP(-Input_Pricing!$D$11*W13)*AB13 -> 6.2172534
C14: 90 | D14: =(LN(C14/Input_Pricing!$D$7)+(Input_Pricing!$D$9-Input_Pricing!$D$11+0.5*Input_Pricing!$D$10^2)*Input_Pricing!$D$8)/(Input_Pricing!$D$10*SQRT(Input_Pricing!$D$8)) -> -0.17680258 | E14: =D14-Input_Pricing!$D$10*SQRT(Input_Pricing!$D$8) -> -0.37680258 | F14: =_xlfn.NORM.S.DIST(D14,TRUE) -> 0.42983173 | G14: =_xlfn.NORM.S.DIST(E14,TRUE) -> 0.35316016 | H14: =_xlfn.NORM.S.DIST(-D14,TRUE) -> 0.57016827 | I14: =_xlfn.NORM.S.DIST(-E14,TRUE) -> 0.64683984 | J14: =C14*EXP(-Input_Pricing!$D$11*Input_Pricing!$D$8)*F14-Input_Pricing!$D$7*EXP(-Input_Pricing!$D$9*Input_Pricing!$D$8)*G14 -> 5.0912221 | K14: =Input_Pricing!$D$7*EXP(-Input_Pricing!$D$9*Input_Pricing!$D$8)*I14-C14*EXP(-Input_Pricing!$D$11*Input_Pricing!$D$8)*H14 -> 10.214165 | M14: 0.35 | N14: =(LN(Input_Pricing!$D$6/Input_Pricing!$D$7)+(Input_Pricing!$D$9-Input_Pricing!$D$11+0.5*M14^2)*Input_Pricing!$D$8)/(M14*SQRT(Input_Pricing!$D$8)) -> 0.31785714 | O14: =N14-M14*SQRT(Input_Pricing!$D$8) -> -0.032142857 | P14: =_xlfn.NORM.S.DIST(N14,TRUE) -> 0.62470335 | Q14: =_xlfn.NORM.S.DIST(O14,TRUE) -> 0.48717906 | R14: =_xlfn.NORM.S.DIST(-N14,TRUE) -> 0.37529665 | S14: =_xlfn.NORM.S.DIST(-O14,TRUE) -> 0.51282094 | T14: =Input_Pricing!$D$6*EXP(-Input_Pricing!$D$11*Input_Pricing!$D$8)*P14-Input_Pricing!$D$7*EXP(-Input_Pricing!$D$9*Input_Pricing!$D$8)*Q14 -> 16.128429 | U14: =Input_Pricing!$D$7*EXP(-Input_Pricing!$D$9*Input_Pricing!$D$8)*S14-Input_Pricing!$D$6*EXP(-Input_Pricing!$D$11*Input_Pricing!$D$8)*R14 -> 11.251371 | W14: 2 | X14: =(LN(Input_Pricing!$D$6/Input_Pricing!$D$7)+(Input_Pricing!$D$9-Input_Pricing!$D$11+0.5*Input_Pricing!$D$10^2)*W14)/(Input_Pricing!$D$10*SQRT(W14)) -> 0.49497475 | Y14: =X14-Input_Pricing!$D$10*SQRT(W14) -> 0.21213203 | Z14: =_xlfn.NORM.S.DIST(X14,TRUE) -> 0.68969103 | AA14: =_xlfn.NORM.S.DIST(Y14,TRUE) -> 0.58399799 | AB14: =_xlfn.NORM.S.DIST(-X14,TRUE) -> 0.31030897 | AC14: =_xlfn.NORM.S.DIST(-Y14,TRUE) -> 0.41600201 | AD14: =Input_Pricing!$D$6*EXP(-Input_Pricing!$D$11*W14)*Z14-Input_Pricing!$D$7*EXP(-Input_Pricing!$D$9*W14)*AA14 -> 16.12678 | AE14: =Input_Pricing!$D$7*EXP(-Input_Pricing!$D$9*W14)*AC14-Input_Pricing!$D$6*EXP(-Input_Pricing!$D$11*W14)*AB14 -> 6.6105215
C15: 95 | D15: =(LN(C15/Input_Pricing!$D$7)+(Input_Pricing!$D$9-Input_Pricing!$D$11+0.5*Input_Pricing!$D$10^2)*Input_Pricing!$D$8)/(Input_Pricing!$D$10*SQRT(Input_Pricing!$D$8)) -> 0.093533528 | E15: =D15-Input_Pricing!$D$10*SQRT(Input_Pricing!$D$8) -> -0.10646647 | F15: =_xlfn.NORM.S.DIST(D15,TRUE) -> 0.53726014 | G15: =_xlfn.NORM.S.DIST(E15,TRUE) -> 0.45760613 | H15: =_xlfn.NORM.S.DIST(-D15,TRUE) -> 0.46273986 | I15: =_xlfn.NORM.S.DIST(-E15,TRUE) -> 0.54239387 | J15: =C15*EXP(-Input_Pricing!$D$11*Input_Pricing!$D$8)*F15-Input_Pricing!$D$7*EXP(-Input_Pricing!$D$9*Input_Pricing!$D$8)*G15 -> 7.5108722 | K15: =Input_Pricing!$D$7*EXP(-Input_Pricing!$D$9*Input_Pricing!$D$8)*I15-C15*EXP(-Input_Pricing!$D$11*Input_Pricing!$D$8)*H15 -> 7.6338146 | M15: 0.4 | N15: =(LN(Input_Pricing!$D$6/Input_Pricing!$D$7)+(Input_Pricing!$D$9-Input_Pricing!$D$11+0.5*M15^2)*Input_Pricing!$D$8)/(M15*SQRT(Input_Pricing!$D$8)) -> 0.325 | O15: =N15-M15*SQRT(Input_Pricing!$D$8) -> -0.075 | P15: =_xlfn.NORM.S.DIST(N15,TRUE) -> 0.62740946 | Q15: =_xlfn.NORM.S.DIST(O15,TRUE) -> 0.47010736 | R15: =_xlfn.NORM.S.DIST(-N15,TRUE) -> 0.37259054 | S15: =_xlfn.NORM.S.DIST(-O15,TRUE) -> 0.52989264 | T15: =Input_Pricing!$D$6*EXP(-Input_Pricing!$D$11*Input_Pricing!$D$8)*P15-Input_Pricing!$D$7*EXP(-Input_Pricing!$D$9*Input_Pricing!$D$8)*Q15 -> 18.022951 | U15: =Input_Pricing!$D$7*EXP(-Input_Pricing!$D$9*Input_Pricing!$D$8)*S15-Input_Pricing!$D$6*EXP(-Input_Pricing!$D$11*Input_Pricing!$D$8)*R15 -> 13.145894 | W15: 3 | X15: =(LN(Input_Pricing!$D$6/Input_Pricing!$D$7)+(Input_Pricing!$D$9-Input_Pricing!$D$11+0.5*Input_Pricing!$D$10^2)*W15)/(Input_Pricing!$D$10*SQRT(W15)) -> 0.60621778 | Y15: =X15-Input_Pricing!$D$10*SQRT(W15) -> 0.25980762 | Z15: =_xlfn.NORM.S.DIST(X15,TRUE) -> 0.72781493 | AA15: =_xlfn.NORM.S.DIST(Y15,TRUE) -> 0.60249391 | AB15: =_xlfn.NORM.S.DIST(-X15,TRUE) -> 0.27218507 | AC15: =_xlfn.NORM.S.DIST(-Y15,TRUE) -> 0.39750609 | AD15: =Input_Pricing!$D$6*EXP(-Input_Pricing!$D$11*W15)*Z15-Input_Pricing!$D$7*EXP(-Input_Pricing!$D$9*W15)*AA15 -> 20.924361 | AE15: =Input_Pricing!$D$7*EXP(-Input_Pricing!$D$9*W15)*AC15-Input_Pricing!$D$6*EXP(-Input_Pricing!$D$11*W15)*AB15 -> 6.9951586
C16: 100 | D16: =(LN(C16/Input_Pricing!$D$7)+(Input_Pricing!$D$9-Input_Pricing!$D$11+0.5*Input_Pricing!$D$10^2)*Input_Pricing!$D$8)/(Input_Pricing!$D$10*SQRT(Input_Pricing!$D$8)) -> 0.35 | E16: =D16-Input_Pricing!$D$10*SQRT(Input_Pricing!$D$8) -> 0.15 | F16: =_xlfn.NORM.S.DIST(D16,TRUE) -> 0.63683065 | G16: =_xlfn.NORM.S.DIST(E16,TRUE) -> 0.55961769 | H16: =_xlfn.NORM.S.DIST(-D16,TRUE) -> 0.36316935 | I16: =_xlfn.NORM.S.DIST(-E16,TRUE) -> 0.44038231 | J16: =C16*EXP(-Input_Pricing!$D$11*Input_Pricing!$D$8)*F16-Input_Pricing!$D$7*EXP(-Input_Pricing!$D$9*Input_Pricing!$D$8)*G16 -> 10.450584 | K16: =Input_Pricing!$D$7*EXP(-Input_Pricing!$D$9*Input_Pricing!$D$8)*I16-C16*EXP(-Input_Pricing!$D$11*Input_Pricing!$D$8)*H16 -> 5.573526 | M16: 0.45 | N16: =(LN(Input_Pricing!$D$6/Input_Pricing!$D$7)+(Input_Pricing!$D$9-Input_Pricing!$D$11+0.5*M16^2)*Input_Pricing!$D$8)/(M16*SQRT(Input_Pricing!$D$8)) -> 0.33611111 | O16: =N16-M16*SQRT(Input_Pricing!$D$8) -> -0.11388889 | P16: =_xlfn.NORM.S.DIST(N16,TRUE) -> 0.63160646 | Q16: =_xlfn.NORM.S.DIST(O16,TRUE) -> 0.45466294 | R16: =_xlfn.NORM.S.DIST(-N16,TRUE) -> 0.36839354 | S16: =_xlfn.NORM.S.DIST(-O16,TRUE) -> 0.54533706 | T16: =Input_Pricing!$D$6*EXP(-Input_Pricing!$D$11*Input_Pricing!$D$8)*P16-Input_Pricing!$D$7*EXP(-Input_Pricing!$D$9*Input_Pricing!$D$8)*Q16 -> 19.91177 | U16: =Input_Pricing!$D$7*EXP(-Input_Pricing!$D$9*Input_Pricing!$D$8)*S16-Input_Pricing!$D$6*EXP(-Input_Pricing!$D$11*Input_Pricing!$D$8)*R16 -> 15.034712
C17: 105 | D17: =(LN(C17/Input_Pricing!$D$7)+(Input_Pricing!$D$9-Input_Pricing!$D$11+0.5*Input_Pricing!$D$10^2)*Input_Pricing!$D$8)/(Input_Pricing!$D$10*SQRT(Input_Pricing!$D$8)) -> 0.59395082 | E17: =D17-Input_Pricing!$D$10*SQRT(Input_Pricing!$D$8) -> 0.39395082 | F17: =_xlfn.NORM.S.DIST(D17,TRUE) -> 0.7237275 | G17: =_xlfn.NORM.S.DIST(E17,TRUE) -> 0.65319133 | H17: =_xlfn.NORM.S.DIST(-D17,TRUE) -> 0.2762725 | I17: =_xlfn.NORM.S.DIST(-E17,TRUE) -> 0.34680867 | J17: =C17*EXP(-Input_Pricing!$D$11*Input_Pricing!$D$8)*F17-Input_Pricing!$D$7*EXP(-Input_Pricing!$D$9*Input_Pricing!$D$8)*G17 -> 13.857906 | K17: =Input_Pricing!$D$7*EXP(-Input_Pricing!$D$9*Input_Pricing!$D$8)*I17-C17*EXP(-Input_Pricing!$D$11*Input_Pricing!$D$8)*H17 -> 3.9808487 | M17: 0.5 | N17: =(LN(Input_Pricing!$D$6/Input_Pricing!$D$7)+(Input_Pricing!$D$9-Input_Pricing!$D$11+0.5*M17^2)*Input_Pricing!$D$8)/(M17*SQRT(Input_Pricing!$D$8)) -> 0.35 | O17: =N17-M17*SQRT(Input_Pricing!$D$8) -> -0.15 | P17: =_xlfn.NORM.S.DIST(N17,TRUE) -> 0.63683065 | Q17: =_xlfn.NORM.S.DIST(O17,TRUE) -> 0.44038231 | R17: =_xlfn.NORM.S.DIST(-N17,TRUE) -> 0.36316935 | S17: =_xlfn.NORM.S.DIST(-O17,TRUE) -> 0.55961769 | T17: =Input_Pricing!$D$6*EXP(-Input_Pricing!$D$11*Input_Pricing!$D$8)*P17-Input_Pricing!$D$7*EXP(-Input_Pricing!$D$9*Input_Pricing!$D$8)*Q17 -> 21.792604 | U17: =Input_Pricing!$D$7*EXP(-Input_Pricing!$D$9*Input_Pricing!$D$8)*S17-Input_Pricing!$D$6*EXP(-Input_Pricing!$D$11*Input_Pricing!$D$8)*R17 -> 16.915547
C18: 110 | D18: =(LN(C18/Input_Pricing!$D$7)+(Input_Pricing!$D$9-Input_Pricing!$D$11+0.5*Input_Pricing!$D$10^2)*Input_Pricing!$D$8)/(Input_Pricing!$D$10*SQRT(Input_Pricing!$D$8)) -> 0.8265509 | E18: =D18-Input_Pricing!$D$10*SQRT(Input_Pricing!$D$8) -> 0.6265509 | F18: =_xlfn.NORM.S.DIST(D18,TRUE) -> 0.79575417 | G18: =_xlfn.NORM.S.DIST(E18,TRUE) -> 0.73452317 | H18: =_xlfn.NORM.S.DIST(-D18,TRUE) -> 0.20424583 | I18: =_xlfn.NORM.S.DIST(-E18,TRUE) -> 0.26547683 | J18: =C18*EXP(-Input_Pricing!$D$11*Input_Pricing!$D$8)*F18-Input_Pricing!$D$7*EXP(-Input_Pricing!$D$9*Input_Pricing!$D$8)*G18 -> 17.662954 | K18: =Input_Pricing!$D$7*EXP(-Input_Pricing!$D$9*Input_Pricing!$D$8)*I18-C18*EXP(-Input_Pricing!$D$11*Input_Pricing!$D$8)*H18 -> 2.7858962
C19: 115 | D19: =(LN(C19/Input_Pricing!$D$7)+(Input_Pricing!$D$9-Input_Pricing!$D$11+0.5*Input_Pricing!$D$10^2)*Input_Pricing!$D$8)/(Input_Pricing!$D$10*SQRT(Input_Pricing!$D$8)) -> 1.0488097 | E19: =D19-Input_Pricing!$D$10*SQRT(Input_Pricing!$D$8) -> 0.84880971 | F19: =_xlfn.NORM.S.DIST(D19,TRUE) -> 0.85286715 | G19: =_xlfn.NORM.S.DIST(E19,TRUE) -> 0.80200641 | H19: =_xlfn.NORM.S.DIST(-D19,TRUE) -> 0.14713285 | I19: =_xlfn.NORM.S.DIST(-E19,TRUE) -> 0.19799359 | J19: =C19*EXP(-Input_Pricing!$D$11*Input_Pricing!$D$8)*F19-Input_Pricing!$D$7*EXP(-Input_Pricing!$D$9*Input_Pricing!$D$8)*G19 -> 21.790513 | K19: =Input_Pricing!$D$7*EXP(-Input_Pricing!$D$9*Input_Pricing!$D$8)*I19-C19*EXP(-Input_Pricing!$D$11*Input_Pricing!$D$8)*H19 -> 1.913455
C20: 120 | D20: =(LN(C20/Input_Pricing!$D$7)+(Input_Pricing!$D$9-Input_Pricing!$D$11+0.5*Input_Pricing!$D$10^2)*Input_Pricing!$D$8)/(Input_Pricing!$D$10*SQRT(Input_Pricing!$D$8)) -> 1.2616078 | E20: =D20-Input_Pricing!$D$10*SQRT(Input_Pricing!$D$8) -> 1.0616078 | F20: =_xlfn.NORM.S.DIST(D20,TRUE) -> 0.89645502 | G20: =_xlfn.NORM.S.DIST(E20,TRUE) -> 0.85579311 | H20: =_xlfn.NORM.S.DIST(-D20,TRUE) -> 0.10354498 | I20: =_xlfn.NORM.S.DIST(-E20,TRUE) -> 0.14420689 | J20: =C20*EXP(-Input_Pricing!$D$11*Input_Pricing!$D$8)*F20-Input_Pricing!$D$7*EXP(-Input_Pricing!$D$9*Input_Pricing!$D$8)*G20 -> 26.169044 | K20: =Input_Pricing!$D$7*EXP(-Input_Pricing!$D$9*Input_Pricing!$D$8)*I20-C20*EXP(-Input_Pricing!$D$11*Input_Pricing!$D$8)*H20 -> 1.2919864
C21: 125 | D21: =(LN(C21/Input_Pricing!$D$7)+(Input_Pricing!$D$9-Input_Pricing!$D$11+0.5*Input_Pricing!$D$10^2)*Input_Pricing!$D$8)/(Input_Pricing!$D$10*SQRT(Input_Pricing!$D$8)) -> 1.4657178 | E21: =D21-Input_Pricing!$D$10*SQRT(Input_Pricing!$D$8) -> 1.2657178 | F21: =_xlfn.NORM.S.DIST(D21,TRUE) -> 0.9286374 | G21: =_xlfn.NORM.S.DIST(E21,TRUE) -> 0.89719293 | H21: =_xlfn.NORM.S.DIST(-D21,TRUE) -> 0.071362597 | I21: =_xlfn.NORM.S.DIST(-E21,TRUE) -> 0.10280707 | J21: =C21*EXP(-Input_Pricing!$D$11*Input_Pricing!$D$8)*F21-Input_Pricing!$D$7*EXP(-Input_Pricing!$D$9*Input_Pricing!$D$8)*G21 -> 30.736044 | K21: =Input_Pricing!$D$7*EXP(-Input_Pricing!$D$9*Input_Pricing!$D$8)*I21-C21*EXP(-Input_Pricing!$D$11*Input_Pricing!$D$8)*H21 -> 0.85898675
C22: 130 | D22: =(LN(C22/Input_Pricing!$D$7)+(Input_Pricing!$D$9-Input_Pricing!$D$11+0.5*Input_Pricing!$D$10^2)*Input_Pricing!$D$8)/(Input_Pricing!$D$10*SQRT(Input_Pricing!$D$8)) -> 1.6618213 | E22: =D22-Input_Pricing!$D$10*SQRT(Input_Pricing!$D$8) -> 1.4618213 | F22: =_xlfn.NORM.S.DIST(D22,TRUE) -> 0.9517257 | G22: =_xlfn.NORM.S.DIST(E22,TRUE) -> 0.92810491 | H22: =_xlfn.NORM.S.DIST(-D22,TRUE) -> 0.048274303 | I22: =_xlfn.NORM.S.DIST(-E22,TRUE) -> 0.07189509 | J22: =C22*EXP(-Input_Pricing!$D$11*Input_Pricing!$D$8)*F22-Input_Pricing!$D$7*EXP(-Input_Pricing!$D$9*Input_Pricing!$D$8)*G22 -> 35.440271 | K22: =Input_Pricing!$D$7*EXP(-Input_Pricing!$D$9*Input_Pricing!$D$8)*I22-C22*EXP(-Input_Pricing!$D$11*Input_Pricing!$D$8)*H22 -> 0.56321312
C23: 135 | D23: =(LN(C23/Input_Pricing!$D$7)+(Input_Pricing!$D$9-Input_Pricing!$D$11+0.5*Input_Pricing!$D$10^2)*Input_Pricing!$D$8)/(Input_Pricing!$D$10*SQRT(Input_Pricing!$D$8)) -> 1.850523 | E23: =D23-Input_Pricing!$D$10*SQRT(Input_Pricing!$D$8) -> 1.650523 | F23: =_xlfn.NORM.S.DIST(D23,TRUE) -> 0.96788089 | G23: =_xlfn.NORM.S.DIST(E23,TRUE) -> 0.95058199 | H23: =_xlfn.NORM.S.DIST(-D23,TRUE) -> 0.032119106 | I23: =_xlfn.NORM.S.DIST(-E23,TRUE) -> 0.04941801 | J23: =C23*EXP(-Input_Pricing!$D$11*Input_Pricing!$D$8)*F23-Input_Pricing!$D$7*EXP(-Input_Pricing!$D$9*Input_Pricing!$D$8)*G23 -> 40.241765 | K23: =Input_Pricing!$D$7*EXP(-Input_Pricing!$D$9*Input_Pricing!$D$8)*I23-C23*EXP(-Input_Pricing!$D$11*Input_Pricing!$D$8)*H23 -> 0.36470728
C24: 140 | D24: =(LN(C24/Input_Pricing!$D$7)+(Input_Pricing!$D$9-Input_Pricing!$D$11+0.5*Input_Pricing!$D$10^2)*Input_Pricing!$D$8)/(Input_Pricing!$D$10*SQRT(Input_Pricing!$D$8)) -> 2.0323612 | E24: =D24-Input_Pricing!$D$10*SQRT(Input_Pricing!$D$8) -> 1.8323612 | F24: =_xlfn.NORM.S.DIST(D24,TRUE) -> 0.97894145 | G24: =_xlfn.NORM.S.DIST(E24,TRUE) -> 0.96655119 | H24: =_xlfn.NORM.S.DIST(-D24,TRUE) -> 0.021058552 | I24: =_xlfn.NORM.S.DIST(-E24,TRUE) -> 0.033448814 | J24: =C24*EXP(-Input_Pricing!$D$11*Input_Pricing!$D$8)*F24-Input_Pricing!$D$7*EXP(-Input_Pricing!$D$9*Input_Pricing!$D$8)*G24 -> 45.11061 | K24: =Input_Pricing!$D$7*EXP(-Input_Pricing!$D$9*Input_Pricing!$D$8)*I24-C24*EXP(-Input_Pricing!$D$11*Input_Pricing!$D$8)*H24 -> 0.23355224
E51: Spot Price | F51: d1 | G51: d2 | H51: N(d1) | I51: N(d2) | J51: phi(d1) | K51: Delta Call | L51: Delta Put | M51: Gamma | N51: Vega
E52: 60 | F52: =(LN(E52/Input_Pricing!$D$7)+(Input_Pricing!$D$9-Input_Pricing!$D$11+0.5*Input_Pricing!$D$10^2)*Input_Pricing!$D$8)/(Input_Pricing!$D$10*SQRT(Input_Pricing!$D$8)) -> -2.2041281 | G52: =F52-Input_Pricing!$D$10*SQRT(Input_Pricing!$D$8) -> -2.4041281 | H52: =_xlfn.NORM.S.DIST(F52,TRUE) -> 0.013757668 | I52: =_xlfn.NORM.S.DIST(G52,TRUE) -> 0.0081055454 | J52: =_xlfn.NORM.S.DIST(F52,FALSE) -> 0.035153577 | K52: =EXP(-Input_Pricing!$D$11*Input_Pricing!$D$8)*H52 -> 0.013757668 | L52: =EXP(-Input_Pricing!$D$11*Input_Pricing!$D$8)*(H52-1) -> -0.98624233 | M52: =EXP(-Input_Pricing!$D$11*Input_Pricing!$D$8)*J52/(E52*Input_Pricing!$D$10*SQRT(Input_Pricing!$D$8)) -> 0.0029294647 | N52: =E52*EXP(-Input_Pricing!$D$11*Input_Pricing!$D$8)*J52*SQRT(Input_Pricing!$D$8)/100 -> 0.021092146
E53: 65 | F53: =(LN(E53/Input_Pricing!$D$7)+(Input_Pricing!$D$9-Input_Pricing!$D$11+0.5*Input_Pricing!$D$10^2)*Input_Pricing!$D$8)/(Input_Pricing!$D$10*SQRT(Input_Pricing!$D$8)) -> -1.8039146 | G53: =F53-Input_Pricing!$D$10*SQRT(Input_Pricing!$D$8) -> -2.0039146 | H53: =_xlfn.NORM.S.DIST(F53,TRUE) -> 0.035622349 | I53: =_xlfn.NORM.S.DIST(G53,TRUE) -> 0.022539606 | J53: =_xlfn.NORM.S.DIST(F53,FALSE) -> 0.078395211 | K53: =EXP(-Input_Pricing!$D$11*Input_Pricing!$D$8)*H53 -> 0.035622349 | L53: =EXP(-Input_Pricing!$D$11*Input_Pricing!$D$8)*(H53-1) -> -0.96437765 | M53: =EXP(-Input_Pricing!$D$11*Input_Pricing!$D$8)*J53/(E53*Input_Pricing!$D$10*SQRT(Input_Pricing!$D$8)) -> 0.0060304008 | N53: =E53*EXP(-Input_Pricing!$D$11*Input_Pricing!$D$8)*J53*SQRT(Input_Pricing!$D$8)/100 -> 0.050956887
E54: 70 | F54: =(LN(E54/Input_Pricing!$D$7)+(Input_Pricing!$D$9-Input_Pricing!$D$11+0.5*Input_Pricing!$D$10^2)*Input_Pricing!$D$8)/(Input_Pricing!$D$10*SQRT(Input_Pricing!$D$8)) -> -1.4333747 | G54: =F54-Input_Pricing!$D$10*SQRT(Input_Pricing!$D$8) -> -1.6333747 | H54: =_xlfn.NORM.S.DIST(F54,TRUE) -> 0.075875389 | I54: =_xlfn.NORM.S.DIST(G54,TRUE) -> 0.051195105 | J54: =_xlfn.NORM.S.DIST(F54,FALSE) -> 0.14281287 | K54: =EXP(-Input_Pricing!$D$11*Input_Pricing!$D$8)*H54 -> 0.075875389 | L54: =EXP(-Input_Pricing!$D$11*Input_Pricing!$D$8)*(H54-1) -> -0.92412461 | M54: =EXP(-Input_Pricing!$D$11*Input_Pricing!$D$8)*J54/(E54*Input_Pricing!$D$10*SQRT(Input_Pricing!$D$8)) -> 0.01020092 | N54: =E54*EXP(-Input_Pricing!$D$11*Input_Pricing!$D$8)*J54*SQRT(Input_Pricing!$D$8)/100 -> 0.099969012
E55: 75 | F55: =(LN(E55/Input_Pricing!$D$7)+(Input_Pricing!$D$9-Input_Pricing!$D$11+0.5*Input_Pricing!$D$10^2)*Input_Pricing!$D$8)/(Input_Pricing!$D$10*SQRT(Input_Pricing!$D$8)) -> -1.0884104 | G55: =F55-Input_Pricing!$D$10*SQRT(Input_Pricing!$D$8) -> -1.2884104 | H55: =_xlfn.NORM.S.DIST(F55,TRUE) -> 0.13820699 | I55: =_xlfn.NORM.S.DIST(G55,TRUE) -> 0.098801577 | J55: =_xlfn.NORM.S.DIST(F55,FALSE) -> 0.22063245 | K55: =EXP(-Input_Pricing!$D$11*Input_Pricing!$D$8)*H55 -> 0.13820699 | L55: =EXP(-Input_Pricing!$D$11*Input_Pricing!$D$8)*(H55-1) -> -0.86179301 | M55: =EXP(-Input_Pricing!$D$11*Input_Pricing!$D$8)*J55/(E55*Input_Pricing!$D$10*SQRT(Input_Pricing!$D$8)) -> 0.01470883 | N55: =E55*EXP(-Input_Pricing!$D$11*Input_Pricing!$D$8)*J55*SQRT(Input_Pricing!$D$8)/100 -> 0.16547434
E56: 80 | F56: =(LN(E56/Input_Pricing!$D$7)+(Input_Pricing!$D$9-Input_Pricing!$D$11+0.5*Input_Pricing!$D$10^2)*Input_Pricing!$D$8)/(Input_Pricing!$D$10*SQRT(Input_Pricing!$D$8)) -> -0.76571776 | G56: =F56-Input_Pricing!$D$10*SQRT(Input_Pricing!$D$8) -> -0.96571776 | H56: =_xlfn.NORM.S.DIST(F56,TRUE) -> 0.22192213 | I56: =_xlfn.NORM.S.DIST(G56,TRUE) -> 0.16709272 | J56: =_xlfn.NORM.S.DIST(F56,FALSE) -> 0.29757161 | K56: =EXP(-Input_Pricing!$D$11*Input_Pricing!$D$8)*H56 -> 0.22192213 | L56: =EXP(-Input_Pricing!$D$11*Input_Pricing!$D$8)*(H56-1) -> -0.77807787 | M56: =EXP(-Input_Pricing!$D$11*Input_Pricing!$D$8)*J56/(E56*Input_Pricing!$D$10*SQRT(Input_Pricing!$D$8)) -> 0.018598226 | N56: =E56*EXP(-Input_Pricing!$D$11*Input_Pricing!$D$8)*J56*SQRT(Input_Pricing!$D$8)/100 -> 0.23805729
E57: 85 | F57: =(LN(E57/Input_Pricing!$D$7)+(Input_Pricing!$D$9-Input_Pricing!$D$11+0.5*Input_Pricing!$D$10^2)*Input_Pricing!$D$8)/(Input_Pricing!$D$10*SQRT(Input_Pricing!$D$8)) -> -0.46259465 | G57: =F57-Input_Pricing!$D$10*SQRT(Input_Pricing!$D$8) -> -0.66259465 | H57: =_xlfn.NORM.S.DIST(F57,TRUE) -> 0.32182747 | I57: =_xlfn.NORM.S.DIST(G57,TRUE) -> 0.2537951 | J57: =_xlfn.NORM.S.DIST(F57,FALSE) -> 0.35846099 | K57: =EXP(-Input_Pricing!$D$11*Input_Pricing!$D$8)*H57 -> 0.32182747 | L57: =EXP(-Input_Pricing!$D$11*Input_Pricing!$D$8)*(H57-1) -> -0.67817253 | M57: =EXP(-Input_Pricing!$D$11*Input_Pricing!$D$8)*J57/(E57*Input_Pricing!$D$10*SQRT(Input_Pricing!$D$8)) -> 0.021085941 | N57: =E57*EXP(-Input_Pricing!$D$11*Input_Pricing!$D$8)*J57*SQRT(Input_Pricing!$D$8)/100 -> 0.30469184
E58: 90 | F58: =(LN(E58/Input_Pricing!$D$7)+(Input_Pricing!$D$9-Input_Pricing!$D$11+0.5*Input_Pricing!$D$10^2)*Input_Pricing!$D$8)/(Input_Pricing!$D$10*SQRT(Input_Pricing!$D$8)) -> -0.17680258 | G58: =F58-Input_Pricing!$D$10*SQRT(Input_Pricing!$D$8) -> -0.37680258 | H58: =_xlfn.NORM.S.DIST(F58,TRUE) -> 0.42983173 | I58: =_xlfn.NORM.S.DIST(G58,TRUE) -> 0.35316016 | J58: =_xlfn.NORM.S.DIST(F58,FALSE) -> 0.39275546 | K58: =EXP(-Input_Pricing!$D$11*Input_Pricing!$D$8)*H58 -> 0.42983173 | L58: =EXP(-Input_Pricing!$D$11*Input_Pricing!$D$8)*(H58-1) -> -0.57016827 | M58: =EXP(-Input_Pricing!$D$11*Input_Pricing!$D$8)*J58/(E58*Input_Pricing!$D$10*SQRT(Input_Pricing!$D$8)) -> 0.021819748 | N58: =E58*EXP(-Input_Pricing!$D$11*Input_Pricing!$D$8)*J58*SQRT(Input_Pricing!$D$8)/100 -> 0.35347991
E59: 95 | F59: =(LN(E59/Input_Pricing!$D$7)+(Input_Pricing!$D$9-Input_Pricing!$D$11+0.5*Input_Pricing!$D$10^2)*Input_Pricing!$D$8)/(Input_Pricing!$D$10*SQRT(Input_Pricing!$D$8)) -> 0.093533528 | G59: =F59-Input_Pricing!$D$10*SQRT(Input_Pricing!$D$8) -> -0.10646647 | H59: =_xlfn.NORM.S.DIST(F59,TRUE) -> 0.53726014 | I59: =_xlfn.NORM.S.DIST(G59,TRUE) -> 0.45760613 | J59: =_xlfn.NORM.S.DIST(F59,FALSE) -> 0.39720101 | K59: =EXP(-Input_Pricing!$D$11*Input_Pricing!$D$8)*H59 -> 0.53726014 | L59: =EXP(-Input_Pricing!$D$11*Input_Pricing!$D$8)*(H59-1) -> -0.46273986 | M59: =EXP(-Input_Pricing!$D$11*Input_Pricing!$D$8)*J59/(E59*Input_Pricing!$D$10*SQRT(Input_Pricing!$D$8)) -> 0.020905317 | N59: =E59*EXP(-Input_Pricing!$D$11*Input_Pricing!$D$8)*J59*SQRT(Input_Pricing!$D$8)/100 -> 0.37734096
E60: 100 | F60: =(LN(E60/Input_Pricing!$D$7)+(Input_Pricing!$D$9-Input_Pricing!$D$11+0.5*Input_Pricing!$D$10^2)*Input_Pricing!$D$8)/(Input_Pricing!$D$10*SQRT(Input_Pricing!$D$8)) -> 0.35 | G60: =F60-Input_Pricing!$D$10*SQRT(Input_Pricing!$D$8) -> 0.15 | H60: =_xlfn.NORM.S.DIST(F60,TRUE) -> 0.63683065 | I60: =_xlfn.NORM.S.DIST(G60,TRUE) -> 0.55961769 | J60: =_xlfn.NORM.S.DIST(F60,FALSE) -> 0.37524035 | K60: =EXP(-Input_Pricing!$D$11*Input_Pricing!$D$8)*H60 -> 0.63683065 | L60: =EXP(-Input_Pricing!$D$11*Input_Pricing!$D$8)*(H60-1) -> -0.36316935 | M60: =EXP(-Input_Pricing!$D$11*Input_Pricing!$D$8)*J60/(E60*Input_Pricing!$D$10*SQRT(Input_Pricing!$D$8)) -> 0.018762017 | N60: =E60*EXP(-Input_Pricing!$D$11*Input_Pricing!$D$8)*J60*SQRT(Input_Pricing!$D$8)/100 -> 0.37524035
E61: 105 | F61: =(LN(E61/Input_Pricing!$D$7)+(Input_Pricing!$D$9-Input_Pricing!$D$11+0.5*Input_Pricing!$D$10^2)*Input_Pricing!$D$8)/(Input_Pricing!$D$10*SQRT(Input_Pricing!$D$8)) -> 0.59395082 | G61: =F61-Input_Pricing!$D$10*SQRT(Input_Pricing!$D$8) -> 0.39395082 | H61: =_xlfn.NORM.S.DIST(F61,TRUE) -> 0.7237275 | I61: =_xlfn.NORM.S.DIST(G61,TRUE) -> 0.65319133 | J61: =_xlfn.NORM.S.DIST(F61,FALSE) -> 0.33443012 | K61: =EXP(-Input_Pricing!$D$11*Input_Pricing!$D$8)*H61 -> 0.7237275 | L61: =EXP(-Input_Pricing!$D$11*Input_Pricing!$D$8)*(H61-1) -> -0.2762725 | M61: =EXP(-Input_Pricing!$D$11*Input_Pricing!$D$8)*J61/(E61*Input_Pricing!$D$10*SQRT(Input_Pricing!$D$8)) -> 0.015925244 | N61: =E61*EXP(-Input_Pricing!$D$11*Input_Pricing!$D$8)*J61*SQRT(Input_Pricing!$D$8)/100 -> 0.35115163
E62: 110 | F62: =(LN(E62/Input_Pricing!$D$7)+(Input_Pricing!$D$9-Input_Pricing!$D$11+0.5*Input_Pricing!$D$10^2)*Input_Pricing!$D$8)/(Input_Pricing!$D$10*SQRT(Input_Pricing!$D$8)) -> 0.8265509 | G62: =F62-Input_Pricing!$D$10*SQRT(Input_Pricing!$D$8) -> 0.6265509 | H62: =_xlfn.NORM.S.DIST(F62,TRUE) -> 0.79575417 | I62: =_xlfn.NORM.S.DIST(G62,TRUE) -> 0.73452317 | J62: =_xlfn.NORM.S.DIST(F62,FALSE) -> 0.28350324 | K62: =EXP(-Input_Pricing!$D$11*Input_Pricing!$D$8)*H62 -> 0.79575417 | L62: =EXP(-Input_Pricing!$D$11*Input_Pricing!$D$8)*(H62-1) -> -0.20424583 | M62: =EXP(-Input_Pricing!$D$11*Input_Pricing!$D$8)*J62/(E62*Input_Pricing!$D$10*SQRT(Input_Pricing!$D$8)) -> 0.012886511 | N62: =E62*EXP(-Input_Pricing!$D$11*Input_Pricing!$D$8)*J62*SQRT(Input_Pricing!$D$8)/100 -> 0.31185356
E63: 115 | F63: =(LN(E63/Input_Pricing!$D$7)+(Input_Pricing!$D$9-Input_Pricing!$D$11+0.5*Input_Pricing!$D$10^2)*Input_Pricing!$D$8)/(Input_Pricing!$D$10*SQRT(Input_Pricing!$D$8)) -> 1.0488097 | G63: =F63-Input_Pricing!$D$10*SQRT(Input_Pricing!$D$8) -> 0.84880971 | H63: =_xlfn.NORM.S.DIST(F63,TRUE) -> 0.85286715 | I63: =_xlfn.NORM.S.DIST(G63,TRUE) -> 0.80200641 | J63: =_xlfn.NORM.S.DIST(F63,FALSE) -> 0.23016946 | K63: =EXP(-Input_Pricing!$D$11*Input_Pricing!$D$8)*H63 -> 0.85286715 | L63: =EXP(-Input_Pricing!$D$11*Input_Pricing!$D$8)*(H63-1) -> -0.14713285 | M63: =EXP(-Input_Pricing!$D$11*Input_Pricing!$D$8)*J63/(E63*Input_Pricing!$D$10*SQRT(Input_Pricing!$D$8)) -> 0.010007368 | N63: =E63*EXP(-Input_Pricing!$D$11*Input_Pricing!$D$8)*J63*SQRT(Input_Pricing!$D$8)/100 -> 0.26469488
... E68: 140 | F68: =(LN(E68/Input_Pricing!$D$7)+(Input_Pricing!$D$9-Input_Pricing!$D$11+0.5*Input_Pricing!$D$10^2)*Input_Pricing!$D$8)/(Input_Pricing!$D$10*SQRT(Input_Pricing!$D$8)) -> 2.0323612 | G68: =F68-Input_Pricing!$D$10*SQRT(Input_Pricing!$D$8) -> 1.8323612 | H68: =_xlfn.NORM.S.DIST(F68,TRUE) -> 0.97894145 | I68: =_xlfn.NORM.S.DIST(G68,TRUE) -> 0.96655119 | J68: =_xlfn.NORM.S.DIST(F68,FALSE) -> 0.050580734 | K68: =EXP(-Input_Pricing!$D$11*Input_Pricing!$D$8)*H68 -> 0.97894145 | L68: =EXP(-Input_Pricing!$D$11*Input_Pricing!$D$8)*(H68-1) -> -0.021058552 | M68: =EXP(-Input_Pricing!$D$11*Input_Pricing!$D$8)*J68/(E68*Input_Pricing!$D$10*SQRT(Input_Pricing!$D$8)) -> 0.0018064548 | N68: =E68*EXP(-Input_Pricing!$D$11*Input_Pricing!$D$8)*J68*SQRT(Input_Pricing!$D$8)/100 -> 0.070813028
